saint/__init__.py
saint-0.0.1.dist-info/LICENSE
saint-0.0.1.dist-info/METADATA
saint-0.0.1.dist-info/WHEEL
saint-0.0.1.dist-info/top_level.txt
saint-0.0.1.dist-info/RECORD
