Metadata-Version: 2.1
Name: saint
Version: 0.0.1
Summary: Software Aided Image Nuking Technology
Home-page: https://github.com/deletescape/SAINT
Author: deletescape
Author-email: me@deletescape.ch
License: UNKNOWN
Platform: UNKNOWN
Classifier: Programming Language :: Python :: 3
Classifier: License :: OSI Approved :: MIT License
Classifier: Operating System :: OS Independent
Requires-Dist: pillow (>=5.2.0)
